wsgi_echo_server.py
wsgi_echo_server-0.0.6.dist-info/LICENSE
wsgi_echo_server-0.0.6.dist-info/METADATA
wsgi_echo_server-0.0.6.dist-info/WHEEL
wsgi_echo_server-0.0.6.dist-info/RECORD
