Metadata-Version: 2.1
Name: wsgi-echo-server
Version: 0.0.6
Summary: 
Author: Iuri de Silvio
Author-email: iurisilvio@gmail.com
Requires-Python: >=3.10,<4.0
Classifier: Programming Language :: Python :: 3
Classifier: Programming Language :: Python :: 3.10
Classifier: Programming Language :: Python :: 3.11
Requires-Dist: flask (>=2.2.3,<3.0.0)
Requires-Dist: requests (>=2.28.2,<3.0.0)
Project-URL: Homepage, https://github.com/buserbrasil/wsgi-echo-server
